scrapy_spider_utils/auto_notify.py
scrapy_spider_utils/esclient.py
scrapy_spider_utils/esdupefilter.py
scrapy_spider_utils/eswriter.py
scrapy_spider_utils/login/baseclient.py
scrapy_spider_utils/login/douban_client.py
scrapy_spider_utils/login/douban_login.py
scrapy_spider_utils/mirai_client.py
scrapy_spider_utils/random_ua.py
scrapy_spider_utils-0.0.13.dist-info/WHEEL
scrapy_spider_utils-0.0.13.dist-info/METADATA
scrapy_spider_utils-0.0.13.dist-info/RECORD
