Metadata-Version: 2.1
Name: scrapy-spider-utils
Version: 0.0.13
Summary: scrapy爬虫的一些工具类
License: AGPL-3.0
Author: gwq5210
Author-email: gwq5210@qq.com
Requires-Python: >=3.6,<4.0.0
Classifier: License :: OSI Approved :: GNU Affero General Public License v3
Classifier: Programming Language :: Python :: 3
Classifier: Programming Language :: Python :: 3.6
Classifier: Programming Language :: Python :: 3.7
Classifier: Programming Language :: Python :: 3.8
Classifier: Programming Language :: Python :: 3.9
Classifier: Programming Language :: Python :: 3.10
Classifier: Programming Language :: Python :: 3.11
Requires-Dist: Scrapy (>=2.5.1)
Requires-Dist: elasticsearch (==7.15.0)
Requires-Dist: fake-useragent (>=0.1.11)
Requires-Dist: itemadapter (>=0.4.0)
Requires-Dist: qrcode (>=7.3.1)
Requires-Dist: requests (>=2.28.1)
